basecli/__init__.py
basecli/__main__.py
basecli/validator.py
basecli-0.0.3.dist-info/METADATA
basecli-0.0.3.dist-info/WHEEL
basecli-0.0.3.dist-info/dependency_links.txt
basecli-0.0.3.dist-info/entry_points.txt
basecli-0.0.3.dist-info/top_level.txt
basecli-0.0.3.dist-info/RECORD
